mmaparray
