Metadata-Version: 1.1
Name: mmaparray
Version: 0.2.1
Summary: MMap File-Backed Arrays for Python
Home-page: https://github.com/farsightsec/mmaparray
Author: Henry Stern
Author-email: stern@fsi.io
License: MIT License
Platform: UNKNOWN
Classifier: License :: OSI Approved :: MIT License
Classifier: Programming Language :: Cython
Classifier: Intended Audience :: Developers
Classifier: Programming Language :: Python :: 2.7
Classifier: Programming Language :: Python :: 3
Classifier: Topic :: Software Development :: Libraries
Requires: six
Requires: Cython (>=0.13)
